Door_Contoller.v
/******************************************************************************
*
* Module: Private - Door_Controller
*
* File Name: Door_Controller.v
*
* Description:  Activate push button (user) trigger the Up motor when the Door
*               down and trigger the Down motor when the Door UpUP_Max (Sensor) 
*               becomes high when the Door is completely open.DN_Max (Sensor) 
*               becomes high when the Door is completely close.Always the Door 
*               is completely close or completely open.Finite state machine is 
*               initialized to IDLE state using Asynchronous reset
*               States Diagram:
*               
* Author: Mohamed A. Eladawy
*
*******************************************************************************/
//************************** Port Declaration ********************************//

module Door_Controller (

input      wire        CLK      , //Declaring the Variable As an Input Port with width 1 bit 
input      wire        RST      , //Declaring the Variable As an Input Port with width 1 bit 
input      wire        Activate , //Declaring the Variable As an Input Port with width 1 bit  
input      wire        Up_Max   , //Declaring the Variable As an Input Port with width 1 bit 
input      wire        Dn_Max   , //Declaring the Variable As an Input Port with width 1 bit 
output     reg         Up_M     , //Declaring the Variable As an Output Port with width 1 bit 
output     reg         Dn_M       //Declaring the Variable As an Output Port with width 1 bit 

);

//******************** Parameters Initialization  ******************//

localparam          IDLE  = 2'b00 ,
                    Mv_Up = 2'b01 ,                    
                    Mv_Dn = 2'b10 ;
                    
//******************** Internal Signal Declaration *****************//

reg      [1:0]      current_state ,
                    next_state ;

//************************* The RTL Code ***************************//

/*************** Starting The Sequential Always Block ***************/

always @ (posedge CLK or negedge RST)
 begin
  if(!RST)
    
       begin
 
          current_state <= IDLE ;
          
       end
  else
   
       begin
   
          current_state <= next_state ;
 
       end

 end

/*************** Starting The Combinational Always Block ***************/

always @ (*)
 
 begin
 
   case (current_state)
 
   IDLE   :  begin
             
              Up_M  = 1'b0 ;
              Dn_M  = 1'b0 ;
              
              if(Activate && Up_Max && !Dn_Max)
             
                begin
               
                   next_state = Mv_Dn  ;
               
                end
             
              else if(Activate && Dn_Max && !Up_Max)
             
                begin
             
                 next_state = Mv_Up     ;
             
                end
              
              else   
              
                begin
              
                 next_state = IDLE  ;
              
                end  
             end
             
   Mv_Up  :  begin
              
              Up_M  = 1'b1 ;
              
              if(Up_Max)
            
                begin
            
                 next_state = IDLE  ;
            
                end
            
              else  
                begin
                 next_state = Mv_Up  ;
                end        
             end
  
   Mv_Dn  :  begin
              
              Dn_M  = 1'b1 ;
              
              if(Dn_Max)
               
                begin
               
                 next_state = IDLE  ;
               
                end
             
              else  
             
                begin
             
                 next_state = Mv_Dn  ;
             
                end        
             end
  
   default : 
             begin
             
                 next_state = IDLE  ;
                 Up_M  = 1'b0 ;
                 Dn_M  = 1'b0 ;
             
             end  
   endcase   
 end



/*********************************************************************/

endmodule

Door_Contoller_tb.v
module Door_Controller_tb();
  
  
//-----------------------------------------------------------------------
//                    Signals Decleration  
//-----------------------------------------------------------------------
  reg   Activate_tb;
  reg   UP_Max_tb;
  reg   DN_Max_tb;
  reg   CLK_tb;
  reg   RST_tb;
  wire  UP_M_tb;
  wire  DN_M_tb;
  
//-----------------------------------------------------------------------
//                         Initial BLock   
//-----------------------------------------------------------------------

initial
begin
  
  $dumpfile("Door_Controller.vcd") ;
  $dumpvars ;
  
  //                      initial values
  
    Activate_tb = 1'b0 ;  
    UP_Max_tb = 1'b0 ;    
    DN_Max_tb = 1'b0 ;
    CLK_tb = 1'b0 ;
    RST_tb = 1'b1 ;
    
    
  //                      TEST CASE 1
    
    $display ("TEST CASE 1") ;  
    #3
    Activate_tb = 1'b0 ;  
    UP_Max_tb = 1'b0 ;    
    DN_Max_tb = 1'b0 ;
    #7
    if(UP_M_tb != 0 && DN_M_tb != 0)
      $display ("TEST CASE 1 IS FAILED") ;
    else
      $display ("TEST CASE 1 IS PASSED") ;
      
      
  //                      TEST CASE 2
    
    $display ("TEST CASE 2") ;  
    #3
    Activate_tb = 1'b1 ;  
    UP_Max_tb = 1'b1 ;    
    DN_Max_tb = 1'b0 ;
    #7
    if(UP_M_tb != 0 && DN_M_tb != 1)
      $display ("TEST CASE 2 IS FAILED") ;
    else
      $display ("TEST CASE 2 IS PASSED") ;   
      
      
  //                      TEST CASE 3
    
    $display ("TEST CASE 3") ;  
    #3
    Activate_tb = 1'b0 ;  
    UP_Max_tb = 1'b0 ;    
    DN_Max_tb = 1'b1 ;
    #7
    if(UP_M_tb != 0 && DN_M_tb != 0)
      $display ("TEST CASE 3 IS FAILED") ;
    else
      $display ("TEST CASE 3 IS PASSED") ;  
      
      
   //                      TEST CASE 4
    
    $display ("TEST CASE 4") ;  
    #3
    Activate_tb = 1'b1 ;  
    UP_Max_tb = 1'b0 ;    
    DN_Max_tb = 1'b1 ;
    #7
    if(UP_M_tb != 1 && DN_M_tb != 0)
      $display ("TEST CASE 4 IS FAILED") ;
    else
      $display ("TEST CASE 4 IS PASSED") ;    
      
      
    //                      TEST CASE 5
    
    $display ("TEST CASE 5") ;  
    #3
    Activate_tb = 1'b0 ;  
    UP_Max_tb = 1'b1 ;    
    DN_Max_tb = 1'b0 ;
    #7
    if(UP_M_tb != 0 && DN_M_tb != 0)
      $display ("TEST CASE 5 IS FAILED") ;
    else
      $display ("TEST CASE 5 IS PASSED") ; 
                  
        #100
$finish ;                                                                                      
end
//-----------------------------------------------------------------------
//                        Clock Generator  
//-----------------------------------------------------------------------
  
  always 
  begin
  #4 CLK_tb = 1'b1 ;
  #6 CLK_tb = 1'b0 ;
end
  
  
//-----------------------------------------------------------------------
//                       instaniate design instance   
//-----------------------------------------------------------------------

Door_Controller DUT (
.Activate(Activate_tb),
.Up_Max(UP_Max_tb),
.Dn_Max(DN_Max_tb),
.CLK(CLK_tb),
.RST(RST_tb),
.Up_M(UP_M_tb),
.Dn_M(DN_M_tb)
  );
endmodule

Door_Controller.vcd
$date
	Tue Aug 30 22:48:07 2022
$end
$version
	ModelSim Version 10.1d
$end
$timescale
	1ps
$end
$scope module Door_Controller_tb $end
$var reg 1 ! Activate_tb $end
$var reg 1 " UP_Max_tb $end
$var reg 1 # DN_Max_tb $end
$var reg 1 $ CLK_tb $end
$var reg 1 % RST_tb $end
$var wire 1 & UP_M_tb $end
$var wire 1 ' DN_M_tb $end
$scope module DUT $end
$var parameter 2 ( IDLE $end
$var parameter 2 ) Mv_Up $end
$var parameter 2 * Mv_Dn $end
$var wire 1 + CLK $end
$var wire 1 , RST $end
$var wire 1 - Activate $end
$var wire 1 . Up_Max $end
$var wire 1 / Dn_Max $end
$var reg 1 0 Up_M $end
$var reg 1 1 Dn_M $end
$var reg 2 2 current_state [1:0] $end
$var reg 2 3 next_state [1:0] $end
$upscope $end
$upscope $end
$enddefinitions $end
#0
$dumpvars
0!
0"
0#
0$
1%
00
01
bx 2
b0 3
b0 (
b1 )
b10 *
0&
0'
1,
0+
0/
0.
0-
$end
#4
1$
1+
b0 2
#10
0$
0+
#13
1!
1"
1-
1.
b10 3
#14
1$
1+
b10 2
11
1'
#20
0$
0+
#23
0!
0"
1#
0-
0.
1/
b0 3
#24
1$
1+
b0 2
01
0'
#30
0$
0+
#33
1!
1-
b1 3
#34
1$
1+
b1 2
10
1&
#40
0$
0+
#43
0!
1"
0#
0-
1.
0/
b0 3
#44
1$
1+
b0 2
00
0&
